<?xml version="1.0" ?>
<cv732_13092.txt>
  <sentence id="1">
    <word id="1" info="существительное в единственном числе">think</word>
    <word id="2" info="глагол, герундий/причастие настоящего времени">saying</word>
    <word id="3" info="существительное во множественном числе">x-files</word>
    <word id="4" info="цифра">one</word>
    <word id="5" info="существительное в единственном числе">summer</word>
    <word id="6" info="притяжательное окончание">'s</word>
    <word id="7" info="глагол, причастие прошедшего времени">anticipated</word>
    <word id="8" info="существительное во множественном числе">films</word>
    <word id="9" info="прилагательное">safe</word>
  </sentence>
  <sentence id="2">
    <word id="1" info="цифра">five</word>
    <word id="2" info="существительное во множественном числе">years</word>
    <word id="3" info="существительное во множественном числе">x-files</word>
    <word id="4" info="существительное в единственном числе">television</word>
    <word id="5" info="существительное в единственном числе">show</word>
    <word id="6" info="существительное в единственном числе">developed</word>
    <word id="7" info="глагол, причастие прошедшего времени">dedicated</word>
    <word id="8" info="существительное в единственном числе">fan</word>
    <word id="9" info="существительное в единственном числе">culture</word>
    <word id="10" info="существительное в единственном числе">rabid</word>
    <word id="11" info="существительное в единственном числе">devotion</word>
    <word id="12" info="существительное в единственном числе">series</word>
    <word id="13" info="существительное во множественном числе">rivals</word>
    <word id="14" info="существительное в единственном числе">star</word>
    <word id="15" info="существительное в единственном числе">trek</word>
    <word id="16" info="существительное во множественном числе">fans</word>
  </sentence>
  <sentence id="3">
    <word id="1" info="существительное в единственном числе">premise</word>
    <word id="2" info="существительное в единственном числе">movie</word>
    <word id="3" info="существительное в единственном числе">television</word>
    <word id="4" info="существительное в единственном числе">series</word>
    <word id="5" info="цифра">two</word>
    <word id="6" info="существительное в единственном числе">fbi</word>
    <word id="7" info="существительное во множественном числе">agents</word>
    <word id="8" info="существительное в единственном числе">investigate</word>
    <word id="9" info="существительное в единственном числе">paranormal</word>
    <word id="10" info="существительное в единственном числе">fox</word>
    <word id="11" info="существительное в единственном числе">mulder</word>
    <word id="12" info="существительное в единственном числе">david</word>
    <word id="13" info="существительное в единственном числе">duchovny</word>
    <word id="14" info="существительное в единственном числе">avid</word>
    <word id="15" info="существительное в единственном числе">believer</word>
    <word id="16" info="существительное в единственном числе">quest</word>
    <word id="17" info="глагол, базовая форма">find</word>
    <word id="18" info="существительное в единственном числе">truth</word>
    <word id="19" info="прилагательное">extraterrestrial</word>
    <word id="20" info="существительное в единственном числе">life</word>
    <word id="21" info="существительное во множественном числе">borders</word>
    <word id="22" info="существительное в единственном числе">paranoid</word>
    <word id="23" info="существительное в единственном числе">dana</word>
    <word id="24" info="наречие">scully</word>
    <word id="25" info="существительное в единственном числе">gillian</word>
    <word id="26" info="существительное в единственном числе">anderson</word>
    <word id="27" info="прилагательное">scientific</word>
    <word id="28" info="прилагательное">skeptic</word>
    <word id="29" info="глагол, герундий/причастие настоящего времени">trying</word>
    <word id="30" info="глагол, базовая форма">find</word>
    <word id="31" info="прилагательное">rational</word>
    <word id="32" info="существительное в единственном числе">explanation</word>
    <word id="33" info="существительное в единственном числе">mulder</word>
    <word id="34" info="притяжательное окончание">'s</word>
    <word id="35" info="существительное во множественном числе">flights</word>
    <word id="36" info="существительное в единственном числе">fancy</word>
  </sentence>
  <sentence id="4">
    <word id="1" info="глагол, герундий/причастие настоящего времени">outlining</word>
    <word id="2" info="существительное в единственном числе">plot</word>
    <word id="3" info="существительное во множественном числе">x-files</word>
    <word id="4" info="существительное в единственном числе">movie</word>
    <word id="5" info="наречие">virtually</word>
    <word id="6" info="прилагательное">impossible</word>
    <word id="7" info="предлог/подчинительный союз">since</word>
    <word id="8" info="прилагательное">general</word>
    <word id="9" info="модальный глагол">would</word>
    <word id="10" info="существительное в единственном числе">result</word>
    <word id="11" info="существительное в единственном числе">confusion</word>
    <word id="12" info="наречие">yet</word>
    <word id="13" info="прилагательное">specific</word>
    <word id="14" info="модальный глагол">would</word>
    <word id="15" info="глагол, базовая форма">give</word>
    <word id="16" info="прилагательное">much</word>
    <word id="17" info="наречие">away</word>
  </sentence>
  <sentence id="5">
    <word id="1" info="наречие">nevertheless</word>
    <word id="2" info="существительное в единственном числе">try</word>
  </sentence>
  <sentence id="6">
    <word id="1" info="прилагательное">black</word>
    <word id="2" info="существительное в единственном числе">ooze</word>
    <word id="3" info="прилагательное">extraterrestrial</word>
    <word id="4" info="существительное в единственном числе">virus-like</word>
    <word id="5" info="существительное в единственном числе">substance</word>
    <word id="6" info="глагол, герундий/причастие настоящего времени">threatening</word>
    <word id="7" info="существительное в единственном числе">earth</word>
  </sentence>
  <sentence id="7">
    <word id="1" info="существительное в единственном числе">shadow</word>
    <word id="2" info="существительное в единственном числе">government</word>
    <word id="3" info="прилагательное">aware</word>
    <word id="4" info="существительное во множественном числе">tries</word>
    <word id="5" info="существительное в единственном числе">cover-up</word>
    <word id="6" info="существительное в единственном числе">alien</word>
    <word id="7" info="существительное в единственном числе">existence</word>
  </sentence>
  <sentence id="8">
    <word id="1" info="существительное в единственном числе">mulder</word>
    <word id="2" info="наречие">scully</word>
    <word id="3" info="глагол, базовая форма">know</word>
    <word id="4" info="существительное в единственном числе">truth</word>
    <word id="5" info="существительное в единственном числе">try</word>
    <word id="6" info="глагол, базовая форма">expose</word>
    <word id="7" info="существительное в единственном числе">invasion</word>
    <word id="8" info="существительное в единственном числе">cover-up</word>
  </sentence>
  <sentence id="9">
    <word id="1" info="цифра">three</word>
    <word id="2" info="прилагательное">central</word>
    <word id="3" info="существительное во множественном числе">questions</word>
    <word id="4" info="существительное в единственном числе">heard</word>
    <word id="5" info="глагол, причастие прошедшего времени">asked</word>
    <word id="6" info="существительное в единственном числе">movie</word>
    <word id="7" info="цифра">1</word>
  </sentence>
  <sentence id="10">
    <word id="1" info="наречие">n't</word>
    <word id="2" info="существительное в единственном числе">watch</word>
    <word id="3" info="существительное в единственном числе">series</word>
    <word id="4" info="прилагательное">able</word>
    <word id="5" info="существительное в единственном числе">understand</word>
    <word id="6" info="существительное в единственном числе">movie</word>
  </sentence>
  <sentence id="11">
    <word id="1" info="существительное во множественном числе">yes</word>
  </sentence>
  <sentence id="12">
    <word id="1" info="прилагательное">isolated</word>
    <word id="2" info="прилагательное">individual</word>
    <word id="3" info="существительное в единственном числе">text</word>
    <word id="4" info="существительное во множественном числе">x-files</word>
    <word id="5" info="существительное в единственном числе">stand</word>
    <word id="6" info="наречие">alone</word>
  </sentence>
  <sentence id="13">
    <word id="1" info="глагол, причастие прошедшего времени">given</word>
    <word id="2" info="наречие">enough</word>
    <word id="3" info="существительное в единственном числе">background</word>
    <word id="4" info="существительное в единственном числе">anyone</word>
    <word id="5" info="прилагательное">familiar</word>
    <word id="6" info="существительное в единственном числе">show</word>
    <word id="7" info="существительное в единственном числе">understand</word>
    <word id="8" info="существительное в единственном числе">movie</word>
  </sentence>
  <sentence id="14">
    <word id="1" info="предлог/подчинительный союз">although</word>
    <word id="2" info="прилагательное">secondary</word>
    <word id="3" info="существительное во множественном числе">characters</word>
    <word id="4" info="существительное во множественном числе">histories</word>
    <word id="5" info="модальный глагол">may</word>
    <word id="6" info="существительное в единственном числе">confuse</word>
    <word id="7" info="прилагательное">uninitiated</word>
    <word id="8" info="существительное во множественном числе">characters</word>
    <word id="9" info="прилагательное">essential</word>
    <word id="10" info="существительное в единственном числе">film</word>
  </sentence>
  <sentence id="15">
    <word id="1" info="прилагательное">major</word>
    <word id="2" info="существительное в единственном числе">problem</word>
    <word id="3" info="существительное в единственном числе">trot</word>
    <word id="4" info="существительное в единственном числе">token</word>
    <word id="5" info="прилагательное">secondary</word>
    <word id="6" info="существительное во множественном числе">characters</word>
    <word id="7" info="существительное в единственном числе">series</word>
    <word id="8" info="существительное в единственном числе">appearance</word>
    <word id="9" info="существительное в единственном числе">disappear</word>
    <word id="10" info="наречие">quickly</word>
  </sentence>
  <sentence id="16">
    <word id="1" info="существительное в единственном числе">bring</word>
    <word id="2" info="существительное в единственном числе">superintendent</word>
    <word id="3" info="существительное в единственном числе">skinner</word>
    <word id="4" info="существительное в единственном числе">picture</word>
    <word id="5" info="наречие">first</word>
    <word id="6" info="существительное в единственном числе">place</word>
    <word id="7" info="существительное в единственном числе">sat</word>
    <word id="8" info="наречие">silently</word>
    <word id="9" info="существительное в единственном числе">fbi</word>
    <word id="10" info="прилагательное">internal</word>
    <word id="11" info="существительное во множественном числе">affairs</word>
    <word id="12" info="существительное в единственном числе">committee</word>
  </sentence>
  <sentence id="17">
    <word id="1" info="существительное в единственном числе">bring</word>
    <word id="2" info="существительное в единственном числе">lone</word>
    <word id="3" info="существительное во множественном числе">gunmen</word>
    <word id="4" info="цифра">three</word>
    <word id="5" info="существительное в единственном числе">computer</word>
    <word id="6" info="существительное в единственном числе">geek</word>
    <word id="7" info="существительное в единственном числе">conspiracy</word>
    <word id="8" info="существительное во множественном числе">theorists</word>
    <word id="9" info="наречие">even</word>
    <word id="10" info="существительное в единственном числе">briefer</word>
    <word id="11" info="существительное в единственном числе">appearance</word>
  </sentence>
  <sentence id="18">
    <word id="1" info="существительное во множественном числе">characters</word>
    <word id="2" info="существительное в единственном числе">recurrent</word>
    <word id="3" info="существительное в единственном числе">series</word>
    <word id="4" info="существительное в единственном числе">appearance</word>
    <word id="5" info="существительное в единственном числе">film</word>
    <word id="6" info="существительное в единственном числе">met</word>
    <word id="7" info="существительное во множественном числе">whoops</word>
    <word id="8" info="существительное в единственном числе">audience</word>
    <word id="9" info="глагол, герундий/причастие настоящего времени">suggesting</word>
    <word id="10" info="существительное в единственном числе">popularity</word>
    <word id="11" info="предлог/подчинительный союз">among</word>
    <word id="12" info="существительное во множественном числе">fans</word>
    <word id="13" info="наречие">actually</word>
    <word id="14" info="существительное в единственном числе">audience</word>
    <word id="15" info="модальный глагол">could</word>
    <word id="16" info="существительное в единственном числе">pass</word>
    <word id="17" info="существительное в единственном числе">lone</word>
    <word id="18" info="существительное во множественном числе">gunmen</word>
  </sentence>
  <sentence id="19">
    <word id="1" info="наречие">still</word>
    <word id="2" info="существительное в единственном числе">vanish</word>
    <word id="3" info="наречие">quickly</word>
  </sentence>
  <sentence id="20">
    <word id="1" info="цифра">2</word>
  </sentence>
  <sentence id="21">
    <word id="1" info="существительное в единственном числе">television</word>
    <word id="2" info="существительное в единственном числе">show</word>
    <word id="3" info="наречие">never</word>
    <word id="4" info="глагол, поющий в 3-м лице. настоящее принимает">gives</word>
    <word id="5" info="местоимение">us</word>
    <word id="6" info="существительное во множественном числе">answers</word>
  </sentence>
  <sentence id="22">
    <word id="1" info="существительное в единственном числе">movie</word>
    <word id="2" info="наречие">actually</word>
    <word id="3" info="существительное в единственном числе">explain</word>
    <word id="4" info="существительное во множественном числе">things</word>
  </sentence>
  <sentence id="23">
    <word id="1" info="существительное во множественном числе">yes</word>
  </sentence>
  <sentence id="24">
    <word id="1" info="существительное во множественном числе">x-files</word>
    <word id="2" info="глагол, базовая форма">get</word>
    <word id="3" info="наречие">fairly</word>
    <word id="4" info="прилагательное">complete</word>
    <word id="5" info="существительное в единственном числе">history</word>
    <word id="6" info="прилагательное">black</word>
    <word id="7" info="существительное в единственном числе">ooze</word>
    <word id="8" info="глагол, поющий в 3-м лице. настоящее принимает">wants</word>
  </sentence>
  <sentence id="25">
    <word id="1" info="наречие">finally</word>
    <word id="2" info="глагол, базовая форма">get</word>
    <word id="3" info="глагол, герундий/причастие настоящего времени">understanding</word>
    <word id="4" info="существительное во множественном числе">motivations</word>
    <word id="5" info="предлог/подчинительный союз">behind</word>
    <word id="6" info="существительное в единственном числе">shadow</word>
    <word id="7" info="существительное в единственном числе">government</word>
  </sentence>
  <sentence id="26">
    <word id="1" info="наречие">even</word>
    <word id="2" info="существительное в единственном числе">subtle</word>
    <word id="3" info="существительное во множественном числе">tie-ins</word>
    <word id="4" info="прилагательное">contemporary</word>
    <word id="5" info="существительное в единственном числе">ufo-ology</word>
    <word id="6" info="глагол, герундий/причастие настоящего времени">including</word>
    <word id="7" info="существительное во множественном числе">greys</word>
    <word id="8" info="существительное в единственном числе">roswell</word>
    <word id="9" info="существительное в единственном числе">crash</word>
    <word id="10" info="цифра">1947</word>
  </sentence>
  <sentence id="27">
    <word id="1" info="цифра">3</word>
  </sentence>
  <sentence id="28">
    <word id="1" info="существительное в единственном числе">movie</word>
    <word id="2" info="прилагательное">good</word>
  </sentence>
  <sentence id="29">
    <word id="1" info="существительное во множественном числе">x-files</word>
    <word id="2" info="существительное в единственном числе">dreadful</word>
    <word id="3" info="существительное в единственном числе">movie</word>
    <word id="4" info="существительное во множественном числе">shows</word>
    <word id="5" info="прилагательное">fundamental</word>
    <word id="6" info="существительное во множественном числе">problems</word>
    <word id="7" info="существительное в единственном числе">writer/creator</word>
    <word id="8" info="существительное в единственном числе">chris</word>
    <word id="9" info="существительное в единственном числе">carter</word>
    <word id="10" info="притяжательное окончание">'s</word>
    <word id="11" info="существительное во множественном числе">talents</word>
    <word id="12" info="существительное в единственном числе">relationship</word>
    <word id="13" info="существительное в единственном числе">cinema</word>
    <word id="14" info="существительное в единственном числе">television</word>
  </sentence>
  <sentence id="30">
    <word id="1" info="наречие">first</word>
    <word id="2" info="существительное в единственном числе">screenplay</word>
    <word id="3" info="существительное в единственном числе">series</word>
    <word id="4" info="существительное в единственном числе">creator</word>
    <word id="5" info="существительное в единственном числе">chris</word>
    <word id="6" info="существительное в единственном числе">carter</word>
    <word id="7" info="прилагательное">sloppy</word>
    <word id="8" info="существительное во множественном числе">cliched</word>
  </sentence>
  <sentence id="31">
    <word id="1" info="наречие">approximately</word>
    <word id="2" info="прилагательное">forty-five</word>
    <word id="3" info="существительное во множественном числе">minutes</word>
    <word id="4" info="существительное в единственном числе">length</word>
    <word id="5" info="существительное в единственном числе">television</word>
    <word id="6" info="существительное в единственном числе">episode</word>
    <word id="7" info="существительное в единственном числе">minus</word>
    <word id="8" info="существительное во множественном числе">commercials</word>
    <word id="9" info="существительное в единственном числе">pace</word>
    <word id="10" info="существительное во множественном числе">drops</word>
    <word id="11" info="существительное в единственном числе">snail</word>
    <word id="12" info="притяжательное окончание">'s</word>
    <word id="13" info="существительное в единственном числе">crawl</word>
  </sentence>
  <sentence id="32">
    <word id="1" info="наречие">long</word>
    <word id="2" info="существительное в единственном числе">point</word>
    <word id="3" info="существительное в единственном числе">carter</word>
    <word id="4" info="существительное во множественном числе">attempts</word>
    <word id="5" info="существительное в единственном числе">answer</word>
    <word id="6" info="существительное во множественном числе">questions</word>
    <word id="7" info="существительное в единственном числе">series</word>
    <word id="8" info="существительное в единственном числе">wish</word>
  </sentence>
  <sentence id="33">
    <word id="1" info="существительное во множественном числе">explanations</word>
    <word id="2" info="существительное в единственном числе">trite</word>
    <word id="3" info="прилагательное">ridiculous</word>
    <word id="4" info="цифра">one</word>
    <word id="5" info="модальный глагол">would</word>
    <word id="6" info="глагол, причастие прошедшего времени">preferred</word>
    <word id="7" info="существительное в единственном числе">carter</word>
    <word id="8" info="глагол, прошедшее время">explained</word>
    <word id="9" info="наречие">quite</word>
    <word id="10" info="прилагательное">much</word>
  </sentence>
  <sentence id="34">
    <word id="1" info="прилагательное">willing</word>
    <word id="2" info="существительное в единственном числе">suspend</word>
    <word id="3" info="существительное в единственном числе">disbelief</word>
    <word id="4" info="существительное в единственном числе">fair</word>
    <word id="5" info="существительное в единственном числе">bit</word>
    <word id="6" info="существительное в единственном числе">absurdity</word>
    <word id="7" info="существительное в единственном числе">carter</word>
    <word id="8" info="глагол, поющий в 3-м лице. настоящее принимает">wants</word>
    <word id="9" info="существительное в единственном числе">swallow</word>
    <word id="10" info="прилагательное">much</word>
  </sentence>
  <sentence id="35">
    <word id="1" info="глагол, герундий/причастие настоящего времени">breaking</word>
    <word id="2" info="существительное в единственном числе">suspension</word>
    <word id="3" info="существительное в единственном числе">disbelief</word>
    <word id="4" info="существительное во множественном числе">destroys</word>
    <word id="5" info="существительное в единственном числе">movie</word>
    <word id="6" info="глагол, герундий/причастие настоящего времени">listening</word>
    <word id="7" info="существительное во множественном числе">fans</word>
    <word id="8" info="глагол, базовая форма">leave</word>
    <word id="9" info="существительное в единственном числе">cinema</word>
    <word id="10" info="наречие">maybe</word>
    <word id="11" info="существительное в единственном числе">series</word>
  </sentence>
  <sentence id="36">
    <word id="1" info="существительное во множественном числе">explanations</word>
    <word id="2" info="существительное в единственном числе">absurd</word>
    <word id="3" info="глагол, причастие прошедшего времени">tired</word>
    <word id="4" info="прилагательное">unoriginal</word>
  </sentence>
  <sentence id="37">
    <word id="1" info="существительное во множественном числе">extraterrestrials</word>
    <word id="2" info="существительное в единственном числе">breed</word>
    <word id="3" info="существительное в единственном числе">gestate</word>
    <word id="4" info="предлог/подчинительный союз">like</word>
    <word id="5" info="существительное в единственном числе">alien</word>
    <word id="6" info="существительное в единственном числе">series</word>
    <word id="7" info="существительное в единственном числе">craft</word>
    <word id="8" info="существительное во множественном числе">looks</word>
    <word id="9" info="предлог/подчинительный союз">like</word>
    <word id="10" info="существительное в единственном числе">leftover</word>
    <word id="11" info="существительное в единственном числе">set</word>
    <word id="12" info="существительное в единственном числе">piece</word>
    <word id="13" info="существительное в единственном числе">independence</word>
    <word id="14" info="существительное в единственном числе">day</word>
  </sentence>
  <sentence id="38">
    <word id="1" info="существительное в единственном числе">note</word>
    <word id="2" info="существительное в единственном числе">alien</word>
    <word id="3" info="существительное во множественном числе">movies</word>
    <word id="4" info="существительное в единственном числе">id4</word>
    <word id="5" info="существительное во множественном числе">x-files</word>
    <word id="6" info="цифра">20thcentury</word>
    <word id="7" info="существительное в единственном числе">fox</word>
    <word id="8" info="существительное в единственном числе">studio</word>
    <word id="9" info="глагол, герундий/причастие настоящего времени">beginning</word>
    <word id="10" info="существительное в единственном числе">cannibalize</word>
    <word id="11" info="существительное в единственном числе">think</word>
  </sentence>
  <sentence id="39">
    <word id="1" info="существительное во множественном числе">x-files</word>
    <word id="2" info="прилагательное">noteworthy</word>
    <word id="3" info="существительное в единственном числе">movie</word>
    <word id="4" info="глагол, причастие прошедшего времени">based</word>
    <word id="5" info="существительное в единственном числе">television</word>
    <word id="6" info="существительное в единственном числе">series</word>
    <word id="7" info="глагол, причастие прошедшего времени">produced</word>
    <word id="8" info="существительное в единственном числе">series</word>
    <word id="9" info="наречие">still</word>
    <word id="10" info="глагол, герундий/причастие настоящего времени">running</word>
  </sentence>
  <sentence id="40">
    <word id="1" info="глагол, герундий/причастие настоящего времени">comparing</word>
    <word id="2" info="существительное в единственном числе">movie</word>
    <word id="3" info="существительное в единственном числе">television</word>
    <word id="4" info="существительное в единственном числе">series</word>
    <word id="5" info="прилагательное">certain</word>
    <word id="6" info="существительное во множественном числе">aspects</word>
    <word id="7" info="существительное в единственном числе">respective</word>
    <word id="8" info="существительное во множественном числе">media</word>
    <word id="9" info="существительное в единственном числе">emerge</word>
  </sentence>
  <sentence id="41">
    <word id="1" info="существительное в единственном числе">avoidance</word>
    <word id="2" info="существительное в единственном числе">series</word>
    <word id="3" info="существительное в единственном числе">answer</word>
    <word id="4" info="существительное во множественном числе">questions</word>
    <word id="5" info="глагол, причастие прошедшего времени">raised</word>
    <word id="6" info="существительное во множественном числе">annoyed</word>
    <word id="7" info="глагол, причастие прошедшего времени">frustrated</word>
    <word id="8" info="прилагательное">many</word>
    <word id="9" info="существительное во множественном числе">people</word>
  </sentence>
  <sentence id="42">
    <word id="1" info="наречие">however</word>
    <word id="2" info="наречие">rather</word>
    <word id="3" info="глагол, причастие прошедшего времени">liked</word>
    <word id="4" info="существительное в единственном числе">series</word>
  </sentence>
  <sentence id="43">
    <word id="1" info="существительное в единственном числе">television</word>
    <word id="2" info="существительное во множественном числе">allows</word>
    <word id="3" info="глагол, базовая форма">impose</word>
    <word id="4" info="прилагательное">much</word>
    <word id="5" info="прилагательное">little</word>
    <word id="6" info="существительное в единственном числе">meaning</word>
    <word id="7" info="существительное в единственном числе">show</word>
    <word id="8" info="существительное в единственном числе">want</word>
  </sentence>
  <sentence id="44">
    <word id="1" info="существительное в единственном числе">proverbial</word>
    <word id="2" info="существительное в единственном числе">blank</word>
    <word id="3" info="существительное в единственном числе">screen</word>
    <word id="4" info="существительное в единственном числе">project</word>
    <word id="5" info="существительное во множественном числе">minds</word>
  </sentence>
  <sentence id="45">
    <word id="1" info="существительное в единственном числе">meaning</word>
    <word id="2" info="существительное в единственном числе">television</word>
    <word id="3" info="прилагательное">open</word>
    <word id="4" info="прилагательное">ambiguous</word>
    <word id="5" info="существительное в единственном числе">nature</word>
    <word id="6" info="существительное в единственном числе">medium</word>
  </sentence>
  <sentence id="46">
    <word id="1" info="существительное в единственном числе">cinema</word>
    <word id="2" info="существительное в единственном числе">hand</word>
    <word id="3" info="существительное в единственном числе">opposite</word>
  </sentence>
  <sentence id="47">
    <word id="1" info="существительное во множественном числе">projects</word>
    <word id="2" info="предлог/подчинительный союз">onto</word>
    <word id="3" info="местоимение">us</word>
    <word id="4" info="существительное во множественном числе">filmmakers</word>
    <word id="5" info="существительное в единственном числе">mind</word>
  </sentence>
  <sentence id="48">
    <word id="1" info="существительное во множественном числе">films</word>
    <word id="2" info="существительное в единственном числе">fill</word>
    <word id="3" info="прилагательное">textual</word>
    <word id="4" info="существительное во множественном числе">gaps</word>
    <word id="5" info="наречие">almost</word>
    <word id="6" info="наречие">never</word>
    <word id="7" info="существительное во множественном числе">happens</word>
    <word id="8" info="прилагательное">american</word>
    <word id="9" info="существительное в единственном числе">film</word>
  </sentence>
  <sentence id="49">
    <word id="1" info="существительное в единственном числе">meaning</word>
    <word id="2" info="существительное в единственном числе">cinema</word>
    <word id="3" info="существительное во множественном числе">needs</word>
    <word id="4" info="прилагательное">self-contained</word>
    <word id="5" info="глагол, причастие прошедшего времени">determined</word>
  </sentence>
  <sentence id="50">
    <word id="1" info="существительное во множественном числе">x-files</word>
    <word id="2" info="глагол, причастие прошедшего времени">made</word>
    <word id="3" info="существительное в единственном числе">jump</word>
    <word id="4" info="прилагательное">small</word>
    <word id="5" info="прилагательное">big</word>
    <word id="6" info="существительное в единственном числе">screen</word>
    <word id="7" info="существительное в единственном числе">carter</word>
    <word id="8" info="глагол, причастие прошедшего времени">needed</word>
    <word id="9" info="глагол, базовая форма">take</word>
    <word id="10" info="существительное в единственном числе">consideration</word>
    <word id="11" info="существительное во множественном числе">differences</word>
    <word id="12" info="существительное в единственном числе">medium</word>
    <word id="13" info="наречие">well</word>
  </sentence>
  <sentence id="51">
    <word id="1" info="глагол, герундий/причастие настоящего времени">making</word>
    <word id="2" info="существительное в единственном числе">explicit</word>
    <word id="3" info="существительное в единственном числе">television</word>
    <word id="4" info="существительное в единственном числе">show</word>
    <word id="5" info="существительное в единственном числе">left</word>
    <word id="6" info="существительное в единственном числе">implicit</word>
    <word id="7" info="существительное в единственном числе">carter</word>
    <word id="8" info="существительное во множественном числе">reveals</word>
    <word id="9" info="существительное во множественном числе">limits</word>
    <word id="10" info="существительное в единственном числе">creativity</word>
    <word id="11" info="существительное в единственном числе">skill</word>
  </sentence>
  <sentence id="52">
    <word id="1" info="глагол, базовая форма">say</word>
    <word id="2" info="существительное во множественном числе">fans</word>
    <word id="3" info="глагол, базовая форма">make</word>
    <word id="4" info="существительное в единственном числе">tv</word>
    <word id="5" info="существительное в единственном числе">show</word>
    <word id="6" info="наречие">far</word>
    <word id="7" info="существительное в единственном числе">truth</word>
  </sentence>
  <sentence id="53">
    <word id="1" info="существительное в единственном числе">television</word>
    <word id="2" info="существительное в единственном числе">fan</word>
    <word id="3" info="существительное в единственном числе">culture</word>
    <word id="4" info="модальный глагол">must</word>
    <word id="5" info="глагол, базовая форма">impose</word>
    <word id="6" info="существительное во множественном числе">meanings</word>
    <word id="7" info="существительное в единственном числе">text</word>
    <word id="8" info="существительное в единственном числе">nothing</word>
  </sentence>
  <sentence id="54">
    <word id="1" info="прилагательное">true</word>
    <word id="2" info="глагол, базовая форма">see</word>
    <word id="3" info="существительное в единственном числе">explicit</word>
    <word id="4" info="существительное во множественном числе">x-files</word>
    <word id="5" info="существительное в единственном числе">nothing</word>
  </sentence>
  <sentence id="55">
    <word id="1" info="глагол, герундий/причастие настоящего времени">following</word>
    <word id="2" info="глагол, причастие прошедшего времени">printed</word>
    <word id="3" info="существительное в единственном числе">st</word>
  </sentence>
  <sentence id="56">
    <word id="1" info="существительное в единственном числе">john</word>
    <word id="2" info="притяжательное окончание">'s</word>
    <word id="3" info="существительное в единственном числе">express</word>
    <word id="4" info="существительное в единственном числе">st</word>
  </sentence>
  <sentence id="57">
    <word id="1" info="существительное в единственном числе">john</word>
    <word id="2" info="притяжательное окончание">'s</word>
    <word id="3" info="существительное в единственном числе">newfoundland</word>
    <word id="4" info="существительное в единственном числе">canada</word>
  </sentence>
  <sentence id="58">
    <word id="1" info="существительное во множественном числе">views</word>
    <word id="2" info="существительное во множественном числе">authors</word>
    <word id="3" info="существительное в единственном числе">copyright</word>
    <word id="4" info="существительное в единственном числе">held</word>
    <word id="5" info="существительное в единственном числе">robinson-blackmore</word>
    <word id="6" info="цифра">1998</word>
  </sentence>
  <sentence id="59">
    <word id="1" info="существительное в единственном числе">nbsp</word>
    <word id="2" info="существительное в единственном числе">movie</word>
    <word id="3" info="существительное в единственном числе">review</word>
    <word id="4" info="существительное в единственном числе">mikel</word>
    <word id="5" info="существительное в единственном числе">j</word>
  </sentence>
  <sentence id="60">
    <word id="1" info="существительное в единственном числе">koven</word>
    <word id="2" info="существительное в единственном числе">nbsp</word>
    <word id="3" info="существительное в единственном числе">think</word>
    <word id="4" info="глагол, герундий/причастие настоящего времени">saying</word>
    <word id="5" info="существительное во множественном числе">x-files</word>
    <word id="6" info="цифра">one</word>
    <word id="7" info="существительное в единственном числе">summer</word>
    <word id="8" info="притяжательное окончание">'s</word>
    <word id="9" info="глагол, причастие прошедшего времени">anticipated</word>
    <word id="10" info="существительное во множественном числе">films</word>
    <word id="11" info="прилагательное">safe</word>
  </sentence>
  <sentence id="61">
    <word id="1" info="существительное в единственном числе">nbsp</word>
    <word id="2" info="цифра">five</word>
    <word id="3" info="существительное во множественном числе">years</word>
    <word id="4" info="существительное во множественном числе">x-files</word>
    <word id="5" info="существительное в единственном числе">television</word>
    <word id="6" info="существительное в единственном числе">show</word>
    <word id="7" info="существительное в единственном числе">developed</word>
    <word id="8" info="глагол, причастие прошедшего времени">dedicated</word>
    <word id="9" info="существительное в единственном числе">fan</word>
    <word id="10" info="существительное в единственном числе">culture</word>
    <word id="11" info="существительное в единственном числе">rabid</word>
    <word id="12" info="существительное в единственном числе">devotion</word>
    <word id="13" info="существительное в единственном числе">series</word>
    <word id="14" info="существительное во множественном числе">rivals</word>
    <word id="15" info="существительное в единственном числе">star</word>
    <word id="16" info="существительное в единственном числе">trek</word>
    <word id="17" info="существительное во множественном числе">fans</word>
  </sentence>
  <sentence id="62">
    <word id="1" info="существительное в единственном числе">nbsp</word>
    <word id="2" info="существительное в единственном числе">premise</word>
    <word id="3" info="существительное в единственном числе">movie</word>
    <word id="4" info="существительное в единственном числе">television</word>
    <word id="5" info="существительное в единственном числе">series</word>
    <word id="6" info="цифра">two</word>
    <word id="7" info="существительное в единственном числе">fbi</word>
    <word id="8" info="существительное во множественном числе">agents</word>
    <word id="9" info="существительное в единственном числе">investigate</word>
    <word id="10" info="существительное в единственном числе">paranormal</word>
    <word id="11" info="существительное в единственном числе">fox</word>
    <word id="12" info="существительное в единственном числе">mulder</word>
    <word id="13" info="существительное в единственном числе">david</word>
    <word id="14" info="существительное в единственном числе">duchovny</word>
    <word id="15" info="существительное в единственном числе">avid</word>
    <word id="16" info="существительное в единственном числе">believer</word>
    <word id="17" info="существительное в единственном числе">quest</word>
    <word id="18" info="глагол, базовая форма">find</word>
    <word id="19" info="существительное в единственном числе">truth</word>
    <word id="20" info="прилагательное">extraterrestrial</word>
    <word id="21" info="существительное в единственном числе">life</word>
    <word id="22" info="существительное во множественном числе">borders</word>
    <word id="23" info="существительное в единственном числе">paranoid</word>
    <word id="24" info="существительное в единственном числе">dana</word>
    <word id="25" info="наречие">scully</word>
    <word id="26" info="существительное в единственном числе">gillian</word>
    <word id="27" info="существительное в единственном числе">anderson</word>
    <word id="28" info="прилагательное">scientific</word>
    <word id="29" info="прилагательное">skeptic</word>
    <word id="30" info="глагол, герундий/причастие настоящего времени">trying</word>
    <word id="31" info="глагол, базовая форма">find</word>
    <word id="32" info="прилагательное">rational</word>
    <word id="33" info="существительное в единственном числе">explanation</word>
    <word id="34" info="существительное в единственном числе">mulder</word>
    <word id="35" info="притяжательное окончание">'s</word>
    <word id="36" info="существительное во множественном числе">flights</word>
    <word id="37" info="существительное в единственном числе">fancy</word>
  </sentence>
  <sentence id="63">
    <word id="1" info="существительное в единственном числе">nbsp</word>
    <word id="2" info="глагол, герундий/причастие настоящего времени">outlining</word>
    <word id="3" info="существительное в единственном числе">plot</word>
    <word id="4" info="существительное во множественном числе">x-files</word>
    <word id="5" info="существительное в единственном числе">movie</word>
    <word id="6" info="наречие">virtually</word>
    <word id="7" info="прилагательное">impossible</word>
    <word id="8" info="предлог/подчинительный союз">since</word>
    <word id="9" info="прилагательное">general</word>
    <word id="10" info="модальный глагол">would</word>
    <word id="11" info="существительное в единственном числе">result</word>
    <word id="12" info="существительное в единственном числе">confusion</word>
    <word id="13" info="наречие">yet</word>
    <word id="14" info="прилагательное">specific</word>
    <word id="15" info="модальный глагол">would</word>
    <word id="16" info="глагол, базовая форма">give</word>
    <word id="17" info="прилагательное">much</word>
    <word id="18" info="наречие">away</word>
  </sentence>
  <sentence id="64">
    <word id="1" info="существительное в единственном числе">nbsp</word>
    <word id="2" info="наречие">nevertheless</word>
    <word id="3" info="существительное в единственном числе">try</word>
  </sentence>
  <sentence id="65">
    <word id="1" info="существительное в единственном числе">nbsp</word>
    <word id="2" info="прилагательное">black</word>
    <word id="3" info="существительное в единственном числе">ooze</word>
    <word id="4" info="прилагательное">extraterrestrial</word>
    <word id="5" info="существительное в единственном числе">virus-like</word>
    <word id="6" info="существительное в единственном числе">substance</word>
    <word id="7" info="глагол, герундий/причастие настоящего времени">threatening</word>
    <word id="8" info="существительное в единственном числе">earth</word>
  </sentence>
  <sentence id="66">
    <word id="1" info="существительное в единственном числе">nbsp</word>
    <word id="2" info="существительное в единственном числе">shadow</word>
    <word id="3" info="существительное в единственном числе">government</word>
    <word id="4" info="прилагательное">aware</word>
    <word id="5" info="существительное во множественном числе">tries</word>
    <word id="6" info="существительное в единственном числе">cover-up</word>
    <word id="7" info="существительное в единственном числе">alien</word>
    <word id="8" info="существительное в единственном числе">existence</word>
  </sentence>
  <sentence id="67">
    <word id="1" info="существительное в единственном числе">nbsp</word>
    <word id="2" info="существительное в единственном числе">mulder</word>
    <word id="3" info="наречие">scully</word>
    <word id="4" info="глагол, базовая форма">know</word>
    <word id="5" info="существительное в единственном числе">truth</word>
    <word id="6" info="существительное в единственном числе">try</word>
    <word id="7" info="глагол, базовая форма">expose</word>
    <word id="8" info="существительное в единственном числе">invasion</word>
    <word id="9" info="существительное в единственном числе">cover-up</word>
  </sentence>
  <sentence id="68">
    <word id="1" info="существительное в единственном числе">nbsp</word>
    <word id="2" info="цифра">three</word>
    <word id="3" info="прилагательное">central</word>
    <word id="4" info="существительное во множественном числе">questions</word>
    <word id="5" info="существительное в единственном числе">heard</word>
    <word id="6" info="глагол, причастие прошедшего времени">asked</word>
    <word id="7" info="существительное в единственном числе">movie</word>
    <word id="8" info="существительное в единственном числе">nbsp</word>
    <word id="9" info="цифра">1</word>
  </sentence>
  <sentence id="69">
    <word id="1" info="существительное в единственном числе">nbsp</word>
    <word id="2" info="наречие">n't</word>
    <word id="3" info="существительное в единственном числе">watch</word>
    <word id="4" info="существительное в единственном числе">series</word>
    <word id="5" info="прилагательное">able</word>
    <word id="6" info="существительное в единственном числе">understand</word>
    <word id="7" info="существительное в единственном числе">movie</word>
  </sentence>
  <sentence id="70">
    <word id="1" info="существительное в единственном числе">nbsp</word>
    <word id="2" info="существительное во множественном числе">yes</word>
  </sentence>
  <sentence id="71">
    <word id="1" info="существительное в единственном числе">nbsp</word>
    <word id="2" info="прилагательное">isolated</word>
    <word id="3" info="прилагательное">individual</word>
    <word id="4" info="существительное в единственном числе">text</word>
    <word id="5" info="существительное во множественном числе">x-files</word>
    <word id="6" info="существительное в единственном числе">stand</word>
    <word id="7" info="наречие">alone</word>
  </sentence>
  <sentence id="72">
    <word id="1" info="существительное в единственном числе">nbsp</word>
    <word id="2" info="глагол, причастие прошедшего времени">given</word>
    <word id="3" info="наречие">enough</word>
    <word id="4" info="существительное в единственном числе">background</word>
    <word id="5" info="существительное в единственном числе">anyone</word>
    <word id="6" info="прилагательное">familiar</word>
    <word id="7" info="существительное в единственном числе">show</word>
    <word id="8" info="существительное в единственном числе">understand</word>
    <word id="9" info="существительное в единственном числе">movie</word>
  </sentence>
  <sentence id="73">
    <word id="1" info="существительное в единственном числе">nbsp</word>
    <word id="2" info="предлог/подчинительный союз">although</word>
    <word id="3" info="прилагательное">secondary</word>
    <word id="4" info="существительное во множественном числе">characters</word>
    <word id="5" info="существительное во множественном числе">histories</word>
    <word id="6" info="модальный глагол">may</word>
    <word id="7" info="существительное в единственном числе">confuse</word>
    <word id="8" info="прилагательное">uninitiated</word>
    <word id="9" info="существительное во множественном числе">characters</word>
    <word id="10" info="прилагательное">essential</word>
    <word id="11" info="существительное в единственном числе">film</word>
  </sentence>
  <sentence id="74">
    <word id="1" info="существительное в единственном числе">nbsp</word>
    <word id="2" info="прилагательное">major</word>
    <word id="3" info="существительное в единственном числе">problem</word>
    <word id="4" info="существительное в единственном числе">trot</word>
    <word id="5" info="существительное в единственном числе">token</word>
    <word id="6" info="прилагательное">secondary</word>
    <word id="7" info="существительное во множественном числе">characters</word>
    <word id="8" info="существительное в единственном числе">series</word>
    <word id="9" info="существительное в единственном числе">appearance</word>
    <word id="10" info="существительное в единственном числе">disappear</word>
    <word id="11" info="наречие">quickly</word>
  </sentence>
  <sentence id="75">
    <word id="1" info="существительное в единственном числе">nbsp</word>
    <word id="2" info="существительное в единственном числе">bring</word>
    <word id="3" info="существительное в единственном числе">superintendent</word>
    <word id="4" info="существительное в единственном числе">skinner</word>
    <word id="5" info="существительное в единственном числе">picture</word>
    <word id="6" info="наречие">first</word>
    <word id="7" info="существительное в единственном числе">place</word>
    <word id="8" info="существительное в единственном числе">sat</word>
    <word id="9" info="наречие">silently</word>
    <word id="10" info="существительное в единственном числе">fbi</word>
    <word id="11" info="прилагательное">internal</word>
    <word id="12" info="существительное во множественном числе">affairs</word>
    <word id="13" info="существительное в единственном числе">committee</word>
  </sentence>
  <sentence id="76">
    <word id="1" info="существительное в единственном числе">nbsp</word>
    <word id="2" info="существительное в единственном числе">bring</word>
    <word id="3" info="существительное в единственном числе">lone</word>
    <word id="4" info="существительное во множественном числе">gunmen</word>
    <word id="5" info="цифра">three</word>
    <word id="6" info="существительное в единственном числе">computer</word>
    <word id="7" info="существительное в единственном числе">geek</word>
    <word id="8" info="существительное в единственном числе">conspiracy</word>
    <word id="9" info="существительное во множественном числе">theorists</word>
    <word id="10" info="наречие">even</word>
    <word id="11" info="существительное в единственном числе">briefer</word>
    <word id="12" info="существительное в единственном числе">appearance</word>
  </sentence>
  <sentence id="77">
    <word id="1" info="существительное в единственном числе">nbsp</word>
    <word id="2" info="существительное во множественном числе">characters</word>
    <word id="3" info="существительное в единственном числе">recurrent</word>
    <word id="4" info="существительное в единственном числе">series</word>
    <word id="5" info="существительное в единственном числе">appearance</word>
    <word id="6" info="существительное в единственном числе">film</word>
    <word id="7" info="существительное в единственном числе">met</word>
    <word id="8" info="существительное во множественном числе">whoops</word>
    <word id="9" info="существительное в единственном числе">audience</word>
    <word id="10" info="глагол, герундий/причастие настоящего времени">suggesting</word>
    <word id="11" info="существительное в единственном числе">popularity</word>
    <word id="12" info="предлог/подчинительный союз">among</word>
    <word id="13" info="существительное во множественном числе">fans</word>
    <word id="14" info="наречие">actually</word>
    <word id="15" info="существительное в единственном числе">audience</word>
    <word id="16" info="модальный глагол">could</word>
    <word id="17" info="существительное в единственном числе">pass</word>
    <word id="18" info="существительное в единственном числе">lone</word>
    <word id="19" info="существительное во множественном числе">gunmen</word>
  </sentence>
  <sentence id="78">
    <word id="1" info="существительное в единственном числе">nbsp</word>
    <word id="2" info="наречие">still</word>
    <word id="3" info="существительное в единственном числе">vanish</word>
    <word id="4" info="наречие">quickly</word>
  </sentence>
  <sentence id="79">
    <word id="1" info="существительное в единственном числе">nbsp</word>
    <word id="2" info="цифра">2</word>
  </sentence>
  <sentence id="80">
    <word id="1" info="существительное в единственном числе">nbsp</word>
    <word id="2" info="существительное в единственном числе">television</word>
    <word id="3" info="существительное в единственном числе">show</word>
    <word id="4" info="наречие">never</word>
    <word id="5" info="глагол, поющий в 3-м лице. настоящее принимает">gives</word>
    <word id="6" info="местоимение">us</word>
    <word id="7" info="существительное во множественном числе">answers</word>
  </sentence>
  <sentence id="81">
    <word id="1" info="существительное в единственном числе">nbsp</word>
    <word id="2" info="существительное в единственном числе">movie</word>
    <word id="3" info="наречие">actually</word>
    <word id="4" info="существительное в единственном числе">explain</word>
    <word id="5" info="существительное во множественном числе">things</word>
  </sentence>
  <sentence id="82">
    <word id="1" info="существительное в единственном числе">nbsp</word>
    <word id="2" info="существительное во множественном числе">yes</word>
  </sentence>
  <sentence id="83">
    <word id="1" info="существительное в единственном числе">nbsp</word>
    <word id="2" info="существительное во множественном числе">x-files</word>
    <word id="3" info="глагол, базовая форма">get</word>
    <word id="4" info="наречие">fairly</word>
    <word id="5" info="прилагательное">complete</word>
    <word id="6" info="существительное в единственном числе">history</word>
    <word id="7" info="прилагательное">black</word>
    <word id="8" info="существительное в единственном числе">ooze</word>
    <word id="9" info="глагол, поющий в 3-м лице. настоящее принимает">wants</word>
  </sentence>
  <sentence id="84">
    <word id="1" info="существительное в единственном числе">nbsp</word>
    <word id="2" info="наречие">finally</word>
    <word id="3" info="глагол, базовая форма">get</word>
    <word id="4" info="глагол, герундий/причастие настоящего времени">understanding</word>
    <word id="5" info="существительное во множественном числе">motivations</word>
    <word id="6" info="предлог/подчинительный союз">behind</word>
    <word id="7" info="существительное в единственном числе">shadow</word>
    <word id="8" info="существительное в единственном числе">government</word>
  </sentence>
  <sentence id="85">
    <word id="1" info="существительное в единственном числе">nbsp</word>
    <word id="2" info="наречие">even</word>
    <word id="3" info="существительное в единственном числе">subtle</word>
    <word id="4" info="существительное во множественном числе">tie-ins</word>
    <word id="5" info="прилагательное">contemporary</word>
    <word id="6" info="существительное в единственном числе">ufo-ology</word>
    <word id="7" info="глагол, герундий/причастие настоящего времени">including</word>
    <word id="8" info="существительное во множественном числе">greys</word>
    <word id="9" info="существительное в единственном числе">roswell</word>
    <word id="10" info="существительное в единственном числе">crash</word>
    <word id="11" info="цифра">1947</word>
  </sentence>
  <sentence id="86">
    <word id="1" info="существительное в единственном числе">nbsp</word>
    <word id="2" info="цифра">3</word>
  </sentence>
  <sentence id="87">
    <word id="1" info="существительное в единственном числе">nbsp</word>
    <word id="2" info="существительное в единственном числе">movie</word>
    <word id="3" info="прилагательное">good</word>
  </sentence>
  <sentence id="88">
    <word id="1" info="существительное в единственном числе">nbsp</word>
  </sentence>
  <sentence id="89">
    <word id="1" info="существительное в единственном числе">nbsp</word>
    <word id="2" info="существительное во множественном числе">x-files</word>
    <word id="3" info="существительное в единственном числе">dreadful</word>
    <word id="4" info="существительное в единственном числе">movie</word>
    <word id="5" info="существительное во множественном числе">shows</word>
    <word id="6" info="прилагательное">fundamental</word>
    <word id="7" info="существительное во множественном числе">problems</word>
    <word id="8" info="существительное в единственном числе">writer/creator</word>
    <word id="9" info="существительное в единственном числе">chris</word>
    <word id="10" info="существительное в единственном числе">carter</word>
    <word id="11" info="притяжательное окончание">'s</word>
    <word id="12" info="существительное во множественном числе">talents</word>
    <word id="13" info="существительное в единственном числе">relationship</word>
    <word id="14" info="существительное в единственном числе">cinema</word>
    <word id="15" info="существительное в единственном числе">television</word>
  </sentence>
  <sentence id="90">
    <word id="1" info="существительное в единственном числе">nbsp</word>
    <word id="2" info="наречие">first</word>
    <word id="3" info="существительное в единственном числе">screenplay</word>
    <word id="4" info="существительное в единственном числе">series</word>
    <word id="5" info="существительное в единственном числе">creator</word>
    <word id="6" info="существительное в единственном числе">chris</word>
    <word id="7" info="существительное в единственном числе">carter</word>
    <word id="8" info="прилагательное">sloppy</word>
    <word id="9" info="существительное во множественном числе">cliched</word>
  </sentence>
  <sentence id="91">
    <word id="1" info="существительное в единственном числе">nbsp</word>
    <word id="2" info="наречие">approximately</word>
    <word id="3" info="прилагательное">forty-five</word>
    <word id="4" info="существительное во множественном числе">minutes</word>
    <word id="5" info="существительное в единственном числе">length</word>
    <word id="6" info="существительное в единственном числе">television</word>
    <word id="7" info="существительное в единственном числе">episode</word>
    <word id="8" info="существительное в единственном числе">minus</word>
    <word id="9" info="существительное во множественном числе">commercials</word>
    <word id="10" info="существительное в единственном числе">pace</word>
    <word id="11" info="существительное во множественном числе">drops</word>
    <word id="12" info="существительное в единственном числе">snail</word>
    <word id="13" info="притяжательное окончание">'s</word>
    <word id="14" info="существительное в единственном числе">crawl</word>
  </sentence>
  <sentence id="92">
    <word id="1" info="существительное в единственном числе">nbsp</word>
    <word id="2" info="наречие">long</word>
    <word id="3" info="существительное в единственном числе">point</word>
    <word id="4" info="существительное в единственном числе">carter</word>
    <word id="5" info="существительное во множественном числе">attempts</word>
    <word id="6" info="существительное в единственном числе">answer</word>
    <word id="7" info="существительное во множественном числе">questions</word>
    <word id="8" info="существительное в единственном числе">series</word>
    <word id="9" info="существительное в единственном числе">wish</word>
  </sentence>
  <sentence id="93">
    <word id="1" info="существительное в единственном числе">nbsp</word>
    <word id="2" info="существительное во множественном числе">explanations</word>
    <word id="3" info="существительное в единственном числе">trite</word>
    <word id="4" info="прилагательное">ridiculous</word>
    <word id="5" info="цифра">one</word>
    <word id="6" info="модальный глагол">would</word>
    <word id="7" info="глагол, причастие прошедшего времени">preferred</word>
    <word id="8" info="существительное в единственном числе">carter</word>
    <word id="9" info="глагол, прошедшее время">explained</word>
    <word id="10" info="наречие">quite</word>
    <word id="11" info="прилагательное">much</word>
  </sentence>
  <sentence id="94">
    <word id="1" info="существительное в единственном числе">nbsp</word>
    <word id="2" info="прилагательное">willing</word>
    <word id="3" info="существительное в единственном числе">suspend</word>
    <word id="4" info="существительное в единственном числе">disbelief</word>
    <word id="5" info="существительное в единственном числе">fair</word>
    <word id="6" info="существительное в единственном числе">bit</word>
    <word id="7" info="существительное в единственном числе">absurdity</word>
    <word id="8" info="существительное в единственном числе">carter</word>
    <word id="9" info="глагол, поющий в 3-м лице. настоящее принимает">wants</word>
    <word id="10" info="существительное в единственном числе">swallow</word>
    <word id="11" info="прилагательное">much</word>
  </sentence>
  <sentence id="95">
    <word id="1" info="существительное в единственном числе">nbsp</word>
    <word id="2" info="глагол, герундий/причастие настоящего времени">breaking</word>
    <word id="3" info="существительное в единственном числе">suspension</word>
    <word id="4" info="существительное в единственном числе">disbelief</word>
    <word id="5" info="существительное во множественном числе">destroys</word>
    <word id="6" info="существительное в единственном числе">movie</word>
    <word id="7" info="глагол, герундий/причастие настоящего времени">listening</word>
    <word id="8" info="существительное во множественном числе">fans</word>
    <word id="9" info="глагол, базовая форма">leave</word>
    <word id="10" info="существительное в единственном числе">cinema</word>
    <word id="11" info="наречие">maybe</word>
    <word id="12" info="существительное в единственном числе">series</word>
  </sentence>
  <sentence id="96">
    <word id="1" info="существительное в единственном числе">nbsp</word>
    <word id="2" info="существительное во множественном числе">explanations</word>
    <word id="3" info="существительное в единственном числе">absurd</word>
    <word id="4" info="глагол, причастие прошедшего времени">tired</word>
    <word id="5" info="прилагательное">unoriginal</word>
  </sentence>
  <sentence id="97">
    <word id="1" info="существительное в единственном числе">nbsp</word>
    <word id="2" info="существительное во множественном числе">extraterrestrials</word>
    <word id="3" info="существительное в единственном числе">breed</word>
    <word id="4" info="существительное в единственном числе">gestate</word>
    <word id="5" info="предлог/подчинительный союз">like</word>
    <word id="6" info="существительное в единственном числе">alien</word>
    <word id="7" info="существительное в единственном числе">series</word>
    <word id="8" info="существительное в единственном числе">craft</word>
    <word id="9" info="существительное во множественном числе">looks</word>
    <word id="10" info="предлог/подчинительный союз">like</word>
    <word id="11" info="существительное в единственном числе">leftover</word>
    <word id="12" info="существительное в единственном числе">set</word>
    <word id="13" info="существительное в единственном числе">piece</word>
    <word id="14" info="существительное в единственном числе">independence</word>
    <word id="15" info="существительное в единственном числе">day</word>
  </sentence>
  <sentence id="98">
    <word id="1" info="существительное в единственном числе">nbsp</word>
    <word id="2" info="существительное в единственном числе">note</word>
    <word id="3" info="существительное в единственном числе">alien</word>
    <word id="4" info="существительное во множественном числе">movies</word>
    <word id="5" info="существительное в единственном числе">id4</word>
    <word id="6" info="существительное во множественном числе">x-files</word>
    <word id="7" info="цифра">20thcentury</word>
    <word id="8" info="существительное в единственном числе">fox</word>
    <word id="9" info="существительное в единственном числе">studio</word>
    <word id="10" info="глагол, герундий/причастие настоящего времени">beginning</word>
    <word id="11" info="существительное в единственном числе">cannibalize</word>
    <word id="12" info="существительное в единственном числе">think</word>
  </sentence>
  <sentence id="99">
    <word id="1" info="существительное в единственном числе">nbsp</word>
    <word id="2" info="существительное во множественном числе">x-files</word>
    <word id="3" info="прилагательное">noteworthy</word>
    <word id="4" info="существительное в единственном числе">movie</word>
    <word id="5" info="глагол, причастие прошедшего времени">based</word>
    <word id="6" info="существительное в единственном числе">television</word>
    <word id="7" info="существительное в единственном числе">series</word>
    <word id="8" info="глагол, причастие прошедшего времени">produced</word>
    <word id="9" info="существительное в единственном числе">series</word>
    <word id="10" info="наречие">still</word>
    <word id="11" info="глагол, герундий/причастие настоящего времени">running</word>
  </sentence>
  <sentence id="100">
    <word id="1" info="существительное в единственном числе">nbsp</word>
    <word id="2" info="глагол, герундий/причастие настоящего времени">comparing</word>
    <word id="3" info="существительное в единственном числе">movie</word>
    <word id="4" info="существительное в единственном числе">television</word>
    <word id="5" info="существительное в единственном числе">series</word>
    <word id="6" info="прилагательное">certain</word>
    <word id="7" info="существительное во множественном числе">aspects</word>
    <word id="8" info="существительное в единственном числе">respective</word>
    <word id="9" info="существительное во множественном числе">media</word>
    <word id="10" info="существительное в единственном числе">emerge</word>
  </sentence>
  <sentence id="101">
    <word id="1" info="существительное в единственном числе">nbsp</word>
    <word id="2" info="существительное в единственном числе">avoidance</word>
    <word id="3" info="существительное в единственном числе">series</word>
    <word id="4" info="существительное в единственном числе">answer</word>
    <word id="5" info="существительное во множественном числе">questions</word>
    <word id="6" info="глагол, причастие прошедшего времени">raised</word>
    <word id="7" info="существительное во множественном числе">annoyed</word>
    <word id="8" info="глагол, причастие прошедшего времени">frustrated</word>
    <word id="9" info="прилагательное">many</word>
    <word id="10" info="существительное во множественном числе">people</word>
  </sentence>
  <sentence id="102">
    <word id="1" info="существительное в единственном числе">nbsp</word>
    <word id="2" info="наречие">however</word>
    <word id="3" info="наречие">rather</word>
    <word id="4" info="глагол, причастие прошедшего времени">liked</word>
    <word id="5" info="существительное в единственном числе">series</word>
  </sentence>
  <sentence id="103">
    <word id="1" info="существительное в единственном числе">nbsp</word>
    <word id="2" info="существительное в единственном числе">television</word>
    <word id="3" info="существительное во множественном числе">allows</word>
    <word id="4" info="глагол, базовая форма">impose</word>
    <word id="5" info="прилагательное">much</word>
    <word id="6" info="прилагательное">little</word>
    <word id="7" info="существительное в единственном числе">meaning</word>
    <word id="8" info="существительное в единственном числе">show</word>
    <word id="9" info="существительное в единственном числе">want</word>
  </sentence>
  <sentence id="104">
    <word id="1" info="существительное в единственном числе">nbsp</word>
    <word id="2" info="существительное в единственном числе">proverbial</word>
    <word id="3" info="существительное в единственном числе">blank</word>
    <word id="4" info="существительное в единственном числе">screen</word>
    <word id="5" info="существительное в единственном числе">project</word>
    <word id="6" info="существительное во множественном числе">minds</word>
  </sentence>
  <sentence id="105">
    <word id="1" info="существительное в единственном числе">nbsp</word>
    <word id="2" info="существительное в единственном числе">meaning</word>
    <word id="3" info="существительное в единственном числе">television</word>
    <word id="4" info="прилагательное">open</word>
    <word id="5" info="прилагательное">ambiguous</word>
    <word id="6" info="существительное в единственном числе">nature</word>
    <word id="7" info="существительное в единственном числе">medium</word>
  </sentence>
  <sentence id="106">
    <word id="1" info="существительное в единственном числе">nbsp</word>
    <word id="2" info="существительное в единственном числе">cinema</word>
    <word id="3" info="существительное в единственном числе">hand</word>
    <word id="4" info="существительное в единственном числе">opposite</word>
  </sentence>
  <sentence id="107">
    <word id="1" info="существительное в единственном числе">nbsp</word>
    <word id="2" info="существительное во множественном числе">projects</word>
    <word id="3" info="предлог/подчинительный союз">onto</word>
    <word id="4" info="местоимение">us</word>
    <word id="5" info="существительное во множественном числе">filmmakers</word>
    <word id="6" info="существительное в единственном числе">mind</word>
  </sentence>
  <sentence id="108">
    <word id="1" info="существительное в единственном числе">nbsp</word>
    <word id="2" info="существительное во множественном числе">films</word>
    <word id="3" info="существительное в единственном числе">fill</word>
    <word id="4" info="прилагательное">textual</word>
    <word id="5" info="существительное во множественном числе">gaps</word>
    <word id="6" info="наречие">almost</word>
    <word id="7" info="наречие">never</word>
    <word id="8" info="существительное во множественном числе">happens</word>
    <word id="9" info="прилагательное">american</word>
    <word id="10" info="существительное в единственном числе">film</word>
  </sentence>
  <sentence id="109">
    <word id="1" info="существительное в единственном числе">nbsp</word>
    <word id="2" info="существительное в единственном числе">meaning</word>
    <word id="3" info="существительное в единственном числе">cinema</word>
    <word id="4" info="существительное во множественном числе">needs</word>
    <word id="5" info="прилагательное">self-contained</word>
    <word id="6" info="глагол, причастие прошедшего времени">determined</word>
  </sentence>
  <sentence id="110">
    <word id="1" info="существительное в единственном числе">nbsp</word>
    <word id="2" info="существительное во множественном числе">x-files</word>
    <word id="3" info="глагол, причастие прошедшего времени">made</word>
    <word id="4" info="существительное в единственном числе">jump</word>
    <word id="5" info="прилагательное">small</word>
    <word id="6" info="прилагательное">big</word>
    <word id="7" info="существительное в единственном числе">screen</word>
    <word id="8" info="существительное в единственном числе">carter</word>
    <word id="9" info="глагол, причастие прошедшего времени">needed</word>
    <word id="10" info="глагол, базовая форма">take</word>
    <word id="11" info="существительное в единственном числе">consideration</word>
    <word id="12" info="существительное во множественном числе">differences</word>
    <word id="13" info="существительное в единственном числе">medium</word>
    <word id="14" info="наречие">well</word>
  </sentence>
  <sentence id="111">
    <word id="1" info="существительное в единственном числе">nbsp</word>
  </sentence>
  <sentence id="112">
    <word id="1" info="существительное в единственном числе">nbsp</word>
    <word id="2" info="глагол, герундий/причастие настоящего времени">making</word>
    <word id="3" info="существительное в единственном числе">explicit</word>
    <word id="4" info="существительное в единственном числе">television</word>
    <word id="5" info="существительное в единственном числе">show</word>
    <word id="6" info="существительное в единственном числе">left</word>
    <word id="7" info="существительное в единственном числе">implicit</word>
    <word id="8" info="существительное в единственном числе">carter</word>
    <word id="9" info="существительное во множественном числе">reveals</word>
    <word id="10" info="существительное во множественном числе">limits</word>
    <word id="11" info="существительное в единственном числе">creativity</word>
    <word id="12" info="существительное в единственном числе">skill</word>
  </sentence>
  <sentence id="113">
    <word id="1" info="существительное в единственном числе">nbsp</word>
    <word id="2" info="глагол, базовая форма">say</word>
    <word id="3" info="существительное во множественном числе">fans</word>
    <word id="4" info="глагол, базовая форма">make</word>
    <word id="5" info="существительное в единственном числе">tv</word>
    <word id="6" info="существительное в единственном числе">show</word>
    <word id="7" info="наречие">far</word>
    <word id="8" info="существительное в единственном числе">truth</word>
  </sentence>
  <sentence id="114">
    <word id="1" info="существительное в единственном числе">nbsp</word>
    <word id="2" info="существительное в единственном числе">television</word>
    <word id="3" info="существительное в единственном числе">fan</word>
    <word id="4" info="существительное в единственном числе">culture</word>
    <word id="5" info="модальный глагол">must</word>
    <word id="6" info="глагол, базовая форма">impose</word>
    <word id="7" info="существительное во множественном числе">meanings</word>
    <word id="8" info="существительное в единственном числе">text</word>
    <word id="9" info="существительное в единственном числе">nothing</word>
  </sentence>
  <sentence id="115">
    <word id="1" info="существительное в единственном числе">nbsp</word>
    <word id="2" info="прилагательное">true</word>
    <word id="3" info="глагол, базовая форма">see</word>
    <word id="4" info="существительное в единственном числе">explicit</word>
    <word id="5" info="существительное во множественном числе">x-files</word>
    <word id="6" info="существительное в единственном числе">nothing</word>
  </sentence>
</cv732_13092.txt>
