<?xml version="1.0" ?>
<cv718_11434.txt>
  <sentence id="1">
    <word id="1" info="наречие">usually</word>
    <word id="3" info="существительное в единственном числе">movie</word>
    <word id="6" info="существительное в единственном числе">something</word>
    <word id="10" info="глагол, причастие прошедшего времени">soiled</word>
    <word id="11" info="существительное в единственном числе">rug</word>
    <word id="16" info="прилагательное">big</word>
    <word id="17" info="существительное в единственном числе">lebowski</word>
  </sentence>
  <sentence id="2">
    <word id="2" info="прилагательное">new</word>
    <word id="3" info="существительное в единственном числе">offering</word>
    <word id="6" info="существительное во множественном числе">creators</word>
    <word id="8" info="цифра">1996</word>
    <word id="9" info="притяжательное окончание">'s</word>
    <word id="10" info="прилагательное">critical</word>
    <word id="11" info="существительное в единственном числе">hit</word>
    <word id="12" info="существительное в единственном числе">fargo</word>
    <word id="16" info="глагол, базовая форма">say</word>
    <word id="18" info="прилагательное в превосходной ">least</word>
    <word id="20" info="наречие">wildly</word>
    <word id="21" info="глагол, герундий/причастие настоящего времени">entertaining</word>
  </sentence>
  <sentence id="3">
    <word id="1" info="существительное в единственном числе">originality</word>
    <word id="3" info="наречие">always</word>
    <word id="6" info="прилагательное">strong</word>
    <word id="7" info="существительное в единственном числе">trait</word>
    <word id="10" info="существительное в единственном числе">coen</word>
    <word id="11" info="существительное в единственном числе">brother</word>
    <word id="12" info="притяжательное окончание">'s</word>
    <word id="13" info="существительное во множественном числе">movies</word>
    <word id="17" info="прилагательное">big</word>
    <word id="18" info="существительное в единственном числе">lebowski</word>
    <word id="20" info="наречие">insanely</word>
    <word id="21" info="прилагательное">original</word>
  </sentence>
  <sentence id="4">
    <word id="2" info="существительное во множественном числе">begins</word>
    <word id="3" info="наречие">oddly</word>
    <word id="4" info="наречие">enough</word>
    <word id="6" info="существительное в единственном числе">jeff</word>
    <word id="9" info="существительное в единственном числе">dude</word>
    <word id="11" info="существительное в единственном числе">lebowski</word>
    <word id="13" info="существительное в единственном числе">jeff</word>
    <word id="14" info="существительное во множественном числе">bridges</word>
    <word id="17" info="существительное в единственном числе">mistaken</word>
    <word id="20" info="существительное в единственном числе">millionaire</word>
    <word id="22" info="существительное в единственном числе">jeff</word>
    <word id="25" info="прилагательное">big</word>
    <word id="27" info="существительное в единственном числе">lebowski</word>
    <word id="29" info="существительное в единственном числе">david</word>
    <word id="30" info="существительное в единственном числе">huddleston</word>
    <word id="34" info="притяжательное окончание">'s</word>
    <word id="35" info="существительное в единственном числе">wife</word>
    <word id="37" info="существительное в единственном числе">bunny</word>
    <word id="39" info="существительное в единственном числе">tara</word>
    <word id="40" info="существительное в единственном числе">reid</word>
    <word id="42" info="существительное в единственном числе">owes</word>
    <word id="43" info="существительное в единственном числе">money</word>
    <word id="46" info="существительное в единственном числе">town</word>
  </sentence>
  <sentence id="5">
    <word id="1" info="цифра">two</word>
    <word id="2" info="существительное во множественном числе">goons</word>
    <word id="6" info="существительное в единственном числе">collect</word>
    <word id="8" info="существительное в единственном числе">bunny</word>
    <word id="9" info="притяжательное окончание">'s</word>
    <word id="10" info="существительное в единственном числе">debt</word>
    <word id="11" info="существительное в единственном числе">break</word>
    <word id="13" info="существительное в единственном числе">dude</word>
    <word id="14" info="притяжательное окончание">'s</word>
    <word id="15" info="существительное в единственном числе">house</word>
  </sentence>
  <sentence id="6">
    <word id="2" info="существительное в единственном числе">attempt</word>
    <word id="4" info="существительное в единственном числе">collect</word>
    <word id="6" info="существительное в единственном числе">money</word>
    <word id="8" info="существительное в единственном числе">bunny</word>
    <word id="9" info="существительное в единственном числе">owes</word>
    <word id="12" info="цифра">one</word>
    <word id="15" info="существительное во множественном числе">urinates</word>
    <word id="18" info="существительное в единственном числе">rug</word>
  </sentence>
  <sentence id="7">
    <word id="2" info="прилагательное">next</word>
    <word id="3" info="существительное в единственном числе">day</word>
    <word id="4" info="существительное в единственном числе">dude</word>
    <word id="5" info="существительное во множественном числе">explains</word>
    <word id="7" info="существительное в единственном числе">situation</word>
    <word id="10" info="существительное в единственном числе">bowling</word>
    <word id="11" info="существительное в единственном числе">team</word>
    <word id="13" info="существительное в единственном числе">steve</word>
    <word id="14" info="существительное в единственном числе">buscemi</word>
    <word id="16" info="существительное в единственном числе">john</word>
    <word id="17" info="существительное в единственном числе">goodman</word>
    <word id="19" info="наречие">respectively</word>
  </sentence>
  <sentence id="8">
    <word id="3" info="глагол, причастие прошедшего времени">advised</word>
    <word id="5" info="глагол, базовая форма">go</word>
    <word id="8" info="прилагательное">big</word>
    <word id="9" info="существительное в единственном числе">lebowski</word>
    <word id="11" info="глагол, базовая форма">get</word>
    <word id="14" info="существительное в единственном числе">pay</word>
    <word id="17" info="глагол, причастие прошедшего времени">defiled</word>
    <word id="18" info="существительное в единственном числе">rug</word>
  </sentence>
  <sentence id="9">
    <word id="6" info="наречие">shortly</word>
    <word id="8" info="глагол, поющий в 3-м лице. настоящее принимает">gets</word>
    <word id="9" info="глагол, причастие прошедшего времени">tied</word>
    <word id="13" info="существительное в единственном числе">kidnapping</word>
    <word id="14" info="существительное в единственном числе">caper</word>
  </sentence>
  <sentence id="10">
    <word id="4" info="наречие">extremely</word>
    <word id="5" info="существительное в единственном числе">funny</word>
    <word id="6" info="существительное в единственном числе">movie</word>
    <word id="8" info="существительное во множественном числе">lots</word>
    <word id="10" info="наречие">belly</word>
    <word id="11" info="существительное в единственном числе">laugh</word>
    <word id="12" info="существительное во множественном числе">moments</word>
  </sentence>
  <sentence id="11">
    <word id="2" info="существительное в единственном числе">coen</word>
    <word id="3" info="существительное во множественном числе">brothers</word>
    <word id="5" info="глагол, причастие прошедшего времени">assembled</word>
    <word id="7" info="прилагательное">great</word>
    <word id="8" info="существительное в единственном числе">cast</word>
    <word id="10" info="существительное в единственном числе">play</word>
    <word id="14" info="наречие">perfectly</word>
  </sentence>
  <sentence id="12">
    <word id="1" info="наречие">also</word>
    <word id="2" info="прилагательное">several</word>
    <word id="3" info="прилагательное">great</word>
    <word id="4" info="глагол, герундий/причастие настоящего времени">supporting</word>
    <word id="5" info="существительное во множественном числе">roles</word>
    <word id="7" info="существительное в единственном числе">john</word>
    <word id="8" info="существительное в единственном числе">turturro</word>
    <word id="11" info="существительное в единственном числе">child</word>
    <word id="12" info="глагол, герундий/причастие настоящего времени">molesting</word>
    <word id="13" info="существительное в единственном числе">bowler</word>
    <word id="14" info="глагол, причастие прошедшего времени">named</word>
    <word id="15" info="существительное в единственном числе">jesus</word>
  </sentence>
  <sentence id="13">
    <word id="2" info="существительное в единственном числе">coen</word>
    <word id="3" info="притяжательное окончание">'s</word>
    <word id="4" info="существительное в единственном числе">script</word>
    <word id="5" info="существительное во множественном числе">plays</word>
    <word id="7" info="наречие">perfectly</word>
    <word id="11" info="глагол, поющий в 3-м лице. настоящее принимает">goes</word>
    <word id="12" info="наречие">together</word>
    <word id="14" info="глагол, базовая форма">make</word>
    <word id="16" info="наречие">extremely</word>
    <word id="17" info="глагол, герундий/причастие настоящего времени">entertaining</word>
  </sentence>
  <sentence id="14">
    <word id="2" info="существительное в единственном числе">doubt</word>
    <word id="4" info="существительное в единственном числе">movie</word>
    <word id="7" info="наречие">nearly</word>
    <word id="9" info="прилагательное">popular</word>
    <word id="11" info="существительное в единственном числе">fargo</word>
    <word id="17" info="существительное в единственном числе">wall</word>
    <word id="18" info="существительное во множественном числе">moments</word>
    <word id="19" info="глагол, базовая форма">make</word>
    <word id="22" info="наречие">far</word>
    <word id="24" info="прилагательное в превосходной ">best</word>
    <word id="26" info="цифра">1998</word>
  </sentence>
  <sentence id="15">
    <word id="3" info="предлог/подчинительный союз">like</word>
    <word id="4" info="существительное в единственном числе">anything</word>
    <word id="5" info="наречие">else</word>
    <word id="7" info="существительное в единственном числе">coen</word>
    <word id="8" info="существительное во множественном числе">brothers</word>
    <word id="10" info="глагол, причастие прошедшего времени">done</word>
    <word id="13" info="существительное в единственном числе">love</word>
    <word id="15" info="цифра">one</word>
    <word id="20" info="глагол, базовая форма">give</word>
    <word id="22" info="цифра">one</word>
    <word id="24" info="существительное в единственном числе">try</word>
    <word id="27" info="прилагательное">little</word>
    <word id="28" info="прилагательное">different</word>
  </sentence>
</cv718_11434.txt>
